[
    {
      "categoria": "Grãos",
      "nome": "Arroz branco",
      "preco": 8.64,
      "imagem":"/images/arroz.jpg",
      "descricao":"Marca Coradini, Tipo 1, pacote de 5Kg, imagem ilustrativa, prazo de validade na embalagem"
    },
    {
      "categoria": "Grãos",
      "nome": "Feijão carioca",
      "preco": 11.34,
      "imagem":"/images/feijao.jpg",
      "descricao":"Marca TBCA"
    },
    {
      "categoria": "Laticínios",
      "nome": "Leite integral",
      "preco": 7.78,
      "imagem":"/images/leite.jpg",
      "descricao":"Marca Aurora, UHT Integral, 1 Litro, contém lactose, 3% de gordura"
    },
    {
      "categoria": "Proteínas",
      "nome": "Ovos",
      "preco": 16.9,
      "imagem":"/images/ovos.jpg",
      "descricao":"Marca Mantiqueira, Ovos Jumbo, tamanho família, categoria A, embalagem com 30 unidades"
    },
    {
      "categoria": "Proteínas",
      "nome": "Carne bovina",
      "preco": 36.78,
      "imagem":"/images/carne.jpg",
      "descricao":"Certified Angus Beef, padrões de qualidade, macia, suculenta e saborosa"
    },
    {
      "categoria": "Proteínas",
      "nome": "Frango inteiro",
      "preco": 18.64,
      "imagem":"/images/frango.jpg",
      "descricao":"Marca Sadia, peso aproximado 2.9 Kg, valor por quilo"
    },
    {
      "categoria": "Café da manhã",
      "nome": "Pão francês",
      "preco": 10.24,
      "imagem":"/images/pao.jpg",
      "descricao":"Deve ter entre 50 e 60 gramas, sem coberturas ou adição de amidos"
    },
    {
      "categoria": "Café em grãos",
      "nome": "Café moído",
      "preco": 22.68,
      "imagem":"/images/cafe.jpg",
      "descricao":"Marca Três Corações"
    },
    {
      "categoria": "Café da manhã",
      "nome": "Açúcar cristal",
      "preco": 5.96,
      "imagem":"/images/acucar.jpg",
      "descricao":"Marca Caravelas, Grupo I, Classe Branco, Tipo Cristal, sacarose de cana-de-açúcar"
    },
    {
      "categoria": "Óleos",
      "nome": "Óleo de soja",
      "preco": 13.08,
      "imagem":"/images/oleo.jpg",
      "descricao":""
    },
    {
      "categoria": "Laticínios",
      "nome": "Manteiga",
      "preco": 15.78,
      "imagem":"/images/manteiga.jpg",
      "descricao":"Marca Scala, feita 100% do creme do leite, sem conservantes"
    },
    {
      "categoria": "Laticínios",
      "nome": "Queijo",
      "preco": 57.52,
      "imagem":"/images/queijo.jpg",
      "descricao":""
    },
    {
      "categoria": "Frutas",
      "nome": "Banana prata",
      "preco": 6.9,
      "imagem":"/images/banana.jpg",
      "descricao":"Maior volume de vitamina C, ideal para banana frita e vitaminas"
    },
    {
      "categoria": "Frutas",
      "nome": "Maçã fuji",
      "preco": 13.56,
      "imagem":"/images/maca.jpg",
      "descricao":"Cor vermelha intensa, mais crocante e com acidez marcante."
    },
    {
      "categoria": "Legumes e verduras",
      "nome": "Tomate",
      "preco": 8.64,
      "imagem":"/images/tomate.jpg",
      "descricao":"Fresco, colhido pela madrugada e abrigado dos raios solares."
    },
    {
      "categoria": "Legumes e verduras",
      "nome": "Cenoura",
      "preco": 5.34,
      "imagem":"/images/cenoura.jpg",
      "descricao":"Rica em betacaroteno, importante para a visão, pele e mucosas."
    },
    {
      "categoria": "Legumes e verduras",
      "nome": "Alface",
      "preco": 3.78,
      "imagem":"/images/alface.jpg",
      "descricao":"Verde intenso, grande número de folhas, ótimo sabor e crocância."
    },
    {
      "categoria": "Bebidas",
      "nome": "Cerveja",
      "preco": 6.9,
      "imagem":"/images/cerveja.jpg",
      "descricao":""
    },
    {
      "categoria": "Bebidas",
      "nome": "Refrigerante",
      "preco": 9.96,
      "imagem":"/images/cola.jpg",
      "descricao":""
    },
    {
      "categoria": "Bebidas",
      "nome": "Suco",
      "preco": 11.52,
      "imagem":"/images/suco.jpg",
      "descricao":"Suco de maçã natural adoçado com o próprio açúcar presente na fruta."
    },
    {
      "categoria": "Higiene",
      "nome": "Sabão em pó",
      "preco": 17.08,
      "imagem":"/images/sabao.jpg",
      "descricao":""
    },
    {
      "categoria": "Higiene",
      "nome": "Amaciante",
      "preco": 4.68,
      "imagem":"/images/amaciante.jpg",
      "descricao":""
    },
    {
      "categoria": "Higiene",
      "nome": "Papel higiênico",
      "preco": 24.9,
      "imagem":"/images/papel.jpg",
      "descricao":""
    },
    {
      "categoria": "Higiene",
      "nome": "Sabonete",
      "preco": 3.96,
      "imagem":"/images/sabonete.jpg",
      "descricao":""
    },
    {
      "categoria": "Higiene",
      "nome": "Shampoo",
      "preco": 19.52,
      "imagem":"/images/shampoo.jpg",
      "descricao":""
    },
    {
      "categoria": "Higiene",
      "nome": "Condicionador",
      "preco": 20.68,
      "imagem":"/images/condicionador.jpg",
      "descricao":""
    },
    {
      "categoria": "Higiene",
      "nome": "Desodorante",
      "preco": 15.78,
      "imagem":"/images/desodorante.jpg",
      "descricao":""
    },
    {
      "categoria": "Higiene",
      "nome": "Pasta de dente",
      "preco": 9.12,
      "imagem":"/images/pasta.jpg",
      "descricao":""
    },
    {
      "categoria": "Iluminação",
      "nome": "Lâmpada",
      "preco": 13.56,
      "imagem":"/images/lampada.jpg",
      "descricao":""
    },
    {
      "categoria": "Iluminação",
      "nome": "Vela",
      "preco": 4.68,
      "imagem":"/images/vela.jpg",
      "descricao":""
    }
]  